luna_ws.py
graphene_luna-1.0.0.dist-info/WHEEL
graphene_luna-1.0.0.dist-info/METADATA
graphene_luna-1.0.0.dist-info/licenses/LICENSE
graphene_luna-1.0.0.dist-info/RECORD
