Metadata-Version: 2.1
Name: graphene-luna
Version: 1.0.0
Summary: Websocket backend for GraphQL (Graphene) subscriptions, does not require Django Channels
License: BSDv3
Author-email: Paul Bailey <paul.bailey@cognitivespace.com>
Requires-Python: >=3.10
Requires-Dist: django-ws>=1.0.0
Requires-Dist: graphene-django>=3.1.5
Requires-Dist: websockets>=10.4
Project-URL: homepage, https://github.com/cognitive-space/graphene-luna
